reviewio/__init__.py
reviewio/cli.py
reviewio-0.2.dist-info/METADATA
reviewio-0.2.dist-info/RECORD
reviewio-0.2.dist-info/WHEEL
reviewio-0.2.dist-info/entry_points.txt
reviewio-0.2.dist-info/top_level.txt
