Metadata-Version: 2.1
Name: reviewio
Version: 0.2
Summary: Display statistics of pull request reviewers for your project
Home-page: https://github.com/borzecki/reviewio
Author: borzeckid
Author-email: borzecki.daniel@gmail.com
License: UNKNOWN
Platform: UNKNOWN
Requires-Dist: Click
Requires-Dist: Colorama
Requires-Dist: PyGithub
